LICENSE
MANIFEST.in
README.md
VERSION.txt
setup.py
src/sysfstree/__init__.py
src/sysfstree/sysfstree.py
src/sysfstree.egg-info/PKG-INFO
src/sysfstree.egg-info/SOURCES.txt
src/sysfstree.egg-info/dependency_links.txt
src/sysfstree.egg-info/entry_points.txt
src/sysfstree.egg-info/requires.txt
src/sysfstree.egg-info/top_level.txt
src/sysfstree/__pycache__/__init__.cpython-37.pyc
src/sysfstree/__pycache__/sysfstree.cpython-37.pyc