Metadata-Version: 2.1
Name: sysfstree
Version: 0.1.11
Summary: sysfstree displayes gadget usb information from the ConfigFS and SysFS
Home-page: http://github.com/Belarra/sysfstree
Author: Stuart Lynne
Author-email: stuart.lynne@gmail.com
License: MIT
Download-URL: http://github.com/Belarra/sysfstree.git
Keywords: configfs,sysfs,pi,usb,gadget
Platform: UNKNOWN
Classifier: Programming Language :: Python
Classifier: Development Status :: 3 - Alpha
Classifier: Environment :: Console
Classifier: Intended Audience :: Developers
Classifier: Intended Audience :: System Administrators
Classifier: Operating System :: POSIX
Classifier: License :: OSI Approved :: MIT License
Classifier: Natural Language :: English
Classifier: Topic :: System :: Logging
Classifier: Topic :: Text Processing
Classifier: Topic :: Software Development :: Libraries :: Python Modules
Classifier: Topic :: System :: System Shells
Classifier: Topic :: System :: Systems Administration
